{"pageProps":{"country":{"name":"Canada","topLevelDomain":[".ca"],"alpha2Code":"CA","alpha3Code":"CAN","callingCodes":["1"],"capital":"Ottawa","altSpellings":["CA"],"region":"Americas","subregion":"Northern America","population":36155487,"latlng":[60,-95],"demonym":"Canadian","area":9984670,"gini":32.6,"timezones":["UTC-08:00","UTC-07:00","UTC-06:00","UTC-05:00","UTC-04:00","UTC-03:30"],"borders":["USA"],"nativeName":"Canada","numericCode":"124","currencies":[{"code":"CAD","name":"Canadian dollar","symbol":"$"}],"languages":[{"iso639_1":"en","iso639_2":"eng","name":"English","nativeName":"English"},{"iso639_1":"fr","iso639_2":"fra","name":"French","nativeName":"français"}],"translations":{"de":"Kanada","es":"Canadá","fr":"Canada","ja":"カナダ","it":"Canada","br":"Canadá","pt":"Canadá","nl":"Canada","hr":"Kanada","fa":"کانادا"},"flag":"https://restcountries.eu/data/can.svg","regionalBlocs":[{"acronym":"NAFTA","name":"North American Free Trade Agreement","otherAcronyms":[],"otherNames":["Tratado de Libre Comercio de América del Norte","Accord de Libre-échange Nord-Américain"]}],"cioc":"CAN"}},"__N_SSG":true}